geojson_fixer/__init__.py
geojson_fixer/errors.py
geojson_fixer/geojson_fixer.py
geojson_fixer/schemas.py
geojson_fixer-0.1.1.dist-info/AUTHORS.rst
geojson_fixer-0.1.1.dist-info/LICENSE
geojson_fixer-0.1.1.dist-info/METADATA
geojson_fixer-0.1.1.dist-info/WHEEL
geojson_fixer-0.1.1.dist-info/top_level.txt
geojson_fixer-0.1.1.dist-info/RECORD
