Metadata-Version: 2.1
Name: geojson-fixer
Version: 0.1.1
Summary: Package to fix minor GeoJSON schema violations
Home-page: https://github.com/sugarlata/geojson_fixer
Author: Nathan Sgarlata
Author-email: nathan.sgarlata@gmail.com
License: MIT license
Keywords: geojson_fixer
Platform: UNKNOWN
Classifier: Development Status :: 2 - Pre-Alpha
Classifier: Intended Audience :: Developers
Classifier: License :: OSI Approved :: MIT License
Classifier: Natural Language :: English
Classifier: Programming Language :: Python :: 3
Classifier: Programming Language :: Python :: 3.5
Classifier: Programming Language :: Python :: 3.6
Classifier: Programming Language :: Python :: 3.7
Classifier: Programming Language :: Python :: 3.8
Requires-Python: >=3.5
